pansg/__init__.py
pansg/_cli.py
pansg/_logging.py
pansg/_pool.py
pansg/_version.py
pansg/blastp_2_dagchainer.py
pansg/comp0.rename.pl
pansg/comp1.get.mpi_sh.pl
pansg/comp1_1.get.miniprot.index.pl
pansg/comp2.get.filter.sh.pl
pansg/comp2_1.extend60bp.pl
pansg/comp2_2.filt.codon_60bp.pl
pansg/comp2_3.adjust.gff.pl
pansg/comp3.get.overlapsh.pl
pansg/comp3_1.overlap.gene_miniprot.pl
pansg/comp4.syn.block.bed.pl
pansg/comp5.cluster.tandem.pl
pansg/comp6_1.format.tmp_pansg.pl
pansg/comp6_1.format.tmp_pansg_add.dup.pl
pansg/comp6_2.complement.pansg.pl
pansg/complement.py
pansg/extract_longest_protein.py
pansg/merge.py
pansg/polish.py
pansg/run.complement.sh
pansg-1.0.0.dist-info/METADATA
pansg-1.0.0.dist-info/WHEEL
pansg-1.0.0.dist-info/entry_points.txt
pansg-1.0.0.dist-info/RECORD
